paynlsdk2/__init__.py
paynlsdk2/exceptions.py
paynlsdk2/objects.py
paynlsdk2/validators.py
paynlsdk2/api/__init__.py
paynlsdk2/api/client.py
paynlsdk2/api/requestbase.py
paynlsdk2/api/responsebase.py
paynlsdk2/api/refund/__init__.py
paynlsdk2/api/refund/info.py
paynlsdk2/api/refund/transaction.py
paynlsdk2/api/transaction/__init__.py
paynlsdk2/api/transaction/approve.py
paynlsdk2/api/transaction/capture.py
paynlsdk2/api/transaction/decline.py
paynlsdk2/api/transaction/getbanks.py
paynlsdk2/api/transaction/getservice.py
paynlsdk2/api/transaction/getservicepaymentoptions.py
paynlsdk2/api/transaction/info.py
paynlsdk2/api/transaction/refund.py
paynlsdk2/api/transaction/start.py
paynlsdk2/api/transaction/status.py
paynlsdk2/api/transaction/voidauthorization.py
paynlsdk2/api/validate/__init__.py
paynlsdk2/api/validate/payserverip.py
paynlsdk2/client/__init__.py
paynlsdk2/client/banks.py
paynlsdk2/client/paymentmethods.py
paynlsdk2/client/refund.py
paynlsdk2/client/transaction.py
paynlsdk2/client/validate.py
paynlsdk2/enums/__init__.py
paynlsdk2/enums/enums.py
paynlsdk2-1.0.0.dist-info/LICENSE.md
paynlsdk2-1.0.0.dist-info/METADATA
paynlsdk2-1.0.0.dist-info/WHEEL
paynlsdk2-1.0.0.dist-info/top_level.txt
paynlsdk2-1.0.0.dist-info/RECORD
