Metadata-Version: 2.1
Name: paynlsdk2
Version: 1.0.0
Summary: PayNL2 SDK
Home-page: https://github.com/paynl/python2-sdk
Author: Ing. R.J. van Dongen
Author-email: rogier@sebsoft.nl
License: UNKNOWN
Project-URL: Bug Reports, https://github.com/paynl/python2-sdk/issues
Project-URL: Source, https://github.com/paynl/python2-sdk/
Keywords: PAYNL2,SDK,Python2
Platform: UNKNOWN
Classifier: Programming Language :: Python :: 2.7
Classifier: License :: OSI Approved :: MIT License
Classifier: Operating System :: OS Independent
Classifier: Development Status :: 4 - Beta
Classifier: Intended Audience :: Developers
Classifier: Topic :: Software Development :: Libraries :: Python Modules
Requires-Dist: marshmallow (<3,>=2)
Requires-Dist: requests
Requires-Dist: typing
